paperslacktail
