Metadata-Version: 1.1
Name: paperslacktail
Version: 1.0.3
Summary: stream from papertrail into slack.
Home-page: https://github.com/evanscottgray/paperslacktail
Author: Evan Gray
Author-email: hello@evanscottgray.com
License: Apache Software License
Keywords: slack,papertrail
Platform: UNKNOWN
Classifier: Development Status :: 4 - Beta
Classifier: License :: OSI Approved :: Apache Software License
